frogger/__init__.py
frogger/api.py
frogger/config.py
frogger/model.py
frogger/server.py
frogger/bin/__init__.py
frogger/bin/compute_embeddings.py
frogger/bin/compute_statistics.py
frogger/bin/extract_tts_spectrograms.py
frogger/bin/remove_silence_using_vad.py
frogger/bin/resample.py
frogger/bin/synthesize.py
frogger/bin/train_encoder.py
frogger/bin/train_tts.py
frogger/bin/train_vocoder.py
frogger/bin/tune_wavegrad.py
frogger/config/__init__.py
frogger/config/shared_configs.py
frogger/encoder/__init__.py
frogger/encoder/dataset.py
frogger/encoder/losses.py
frogger/encoder/configs/base_encoder_config.py
frogger/encoder/configs/speaker_encoder_config.py
frogger/encoder/models/base_encoder.py
frogger/encoder/models/lstm.py
frogger/encoder/models/resnet.py
frogger/encoder/utils/__init__.py
frogger/encoder/utils/generic_utils.py
frogger/encoder/utils/io.py
frogger/encoder/utils/prepare_voxceleb.py
frogger/encoder/utils/training.py
frogger/tts/__init__.py
frogger/tts/configs/__init__.py
frogger/tts/configs/shared_configs.py
frogger/tts/configs/vits_config.py
frogger/tts/datasets/__init__.py
frogger/tts/datasets/dataset.py
frogger/tts/datasets/formatters.py
frogger/tts/layers/__init__.py
frogger/tts/layers/losses.py
frogger/tts/layers/generic/__init__.py
frogger/tts/layers/generic/aligner.py
frogger/tts/layers/generic/gated_conv.py
frogger/tts/layers/generic/normalization.py
frogger/tts/layers/generic/pos_encoding.py
frogger/tts/layers/generic/res_conv_bn.py
frogger/tts/layers/generic/time_depth_sep_conv.py
frogger/tts/layers/generic/transformer.py
frogger/tts/layers/generic/wavenet.py
frogger/tts/layers/glow_tts/__init__.py
frogger/tts/layers/glow_tts/decoder.py
frogger/tts/layers/glow_tts/duration_predictor.py
frogger/tts/layers/glow_tts/encoder.py
frogger/tts/layers/glow_tts/glow.py
frogger/tts/layers/glow_tts/transformer.py
frogger/tts/layers/vits/discriminator.py
frogger/tts/layers/vits/networks.py
frogger/tts/layers/vits/stochastic_duration_predictor.py
frogger-0.1.0.dist-info/METADATA
frogger-0.1.0.dist-info/WHEEL
frogger-0.1.0.dist-info/top_level.txt
frogger-0.1.0.dist-info/RECORD
